nutstools/__init__.py
nutstools/_typings.py
nutstools/main.py
nutstools/nutsdata.py
nutstools/postalnuts.py
NutsTools-0.5.5.dist-info/LICENSE.txt
NutsTools-0.5.5.dist-info/METADATA
NutsTools-0.5.5.dist-info/WHEEL
NutsTools-0.5.5.dist-info/entry_points.txt
NutsTools-0.5.5.dist-info/top_level.txt
NutsTools-0.5.5.dist-info/RECORD
