Metadata-Version: 2.1
Name: NutsTools
Version: 0.5.5
Summary: Obtain NUTS codes by postal codes
Home-page: https://github.com/eelcovv/NutsTools
Author: EVLT
Author-email: EVLT@cbs.nl
License: MIT
Project-URL: Documentation, http://nutstools.readthedocs.io/
Platform: any
Classifier: Development Status :: 4 - Beta
Classifier: Programming Language :: Python
License-File: LICENSE.txt
Requires-Dist: appdirs
Requires-Dist: requests
Requires-Dist: pyarrow
Requires-Dist: pandas
Requires-Dist: pyyaml
Requires-Dist: importlib-metadata ; python_version < "3.8"
Provides-Extra: dev
Requires-Dist: tox ; extra == 'dev'
Requires-Dist: pre-commit ; extra == 'dev'
Requires-Dist: pytest ; extra == 'dev'
Provides-Extra: proxy
Requires-Dist: requests-kerberos-proxy ; extra == 'proxy'
Provides-Extra: testing
Requires-Dist: setuptools ; extra == 'testing'
Requires-Dist: pytest ; extra == 'testing'
Requires-Dist: pytest-cov ; extra == 'testing'
